{
"id": 29,
"label": "acceleration slow 20kmh turn left 90°",
"createdAt": "2023-05-05 22:19:57.258",
"tags": {
"id": 76,
"captureSpeed": 250.0,
"gravityFilter": true,
"averageFilter": "Low-Pass Filter",
"elapsedTimeInSeconds": 9
},
"device": {
"id": 1,
"name": "Pieter",
"manufacturer": "samsung",
"brand": "samsung",
"model": "SM-A515F",
"accelerometerMaxRange": 78.45320129394531,
"accelerometerName": "LSM6DSL Accelerometer",
"accelerometerMinDelay": 2000,
"gyroscopeMaxRange": 17.45326042175293,
"gyroscopeName": "LSM6DSL Gyroscope",
"gyroscopeMinDelay": 2000
},
"capturedData": [
{
"id": 822,
"accelerometerXAxis": 0.022848129,
"accelerometerYAxis": 0.014702141,
"accelerometerZAxis": 0.121748924,
"gyroscopeXAxis": 0.000610865,
"gyroscopeYAxis": 0.006108652,
"gyroscopeZAxis": -0.005497787,
"Latitude": 39.817024734802544 ,
"Longitude": -8.624657336622477 ,
"speedKmh": 0.0 ,
"timestamp": "2023-05-05 22:19:57.316"
},
{
"id": 823,
"accelerometerXAxis": 0.151665390,
"accelerometerYAxis": -0.066561043,
"accelerometerZAxis": -0.036887169,
"gyroscopeXAxis": -0.004886922,
"gyroscopeYAxis": 0.014049901,
"gyroscopeZAxis": 0.001832596,
"Latitude": 39.817024734802544 ,
"Longitude": -8.624657336622477 ,
"speedKmh": 0.0 ,
"timestamp": "2023-05-05 22:19:57.566"
},
{
"id": 824,
"accelerometerXAxis": 0.197354585,
"accelerometerYAxis": 0.042730451,
"accelerometerZAxis": -0.079773903,
"gyroscopeXAxis": -0.001221730,
"gyroscopeYAxis": 0.008552114,
"gyroscopeZAxis": -0.003665192,
"Latitude": 39.817024734802544 ,
"Longitude": -8.624657336622477 ,
"speedKmh": 0.0 ,
"timestamp": "2023-05-05 22:19:57.815"
},
{
"id": 825,
"accelerometerXAxis": -0.129004061,
"accelerometerYAxis": -0.149087280,
"accelerometerZAxis": -0.015008926,
"gyroscopeXAxis": -0.004276057,
"gyroscopeYAxis": 0.011606440,
"gyroscopeZAxis": -0.002443461,
"Latitude": 39.817024734802544 ,
"Longitude": -8.624657336622477 ,
"speedKmh": 0.0 ,
"timestamp": "2023-05-05 22:19:58.065"
},
{
"id": 826,
"accelerometerXAxis": 0.062616765,
"accelerometerYAxis": 0.018816411,
"accelerometerZAxis": 0.053571701,
"gyroscopeXAxis": 0.000000000,
"gyroscopeYAxis": -0.010995574,
"gyroscopeZAxis": -0.004886922,
"Latitude": 39.817024734802544 ,
"Longitude": -8.624657336622477 ,
"speedKmh": 0.0 ,
"timestamp": "2023-05-05 22:19:58.315"
},
{
"id": 827,
"accelerometerXAxis": -0.192803264,
"accelerometerYAxis": 0.175069392,
"accelerometerZAxis": -0.469036102,
"gyroscopeXAxis": -0.006719518,
"gyroscopeYAxis": -0.003665192,
"gyroscopeZAxis": -0.008552114,
"Latitude": 39.817024734802544 ,
"Longitude": -8.624657336622477 ,
"speedKmh": 0.0 ,
"timestamp": "2023-05-05 22:19:58.566"
},
{
"id": 828,
"accelerometerXAxis": 0.038044930,
"accelerometerYAxis": 0.567094982,
"accelerometerZAxis": 0.359105110,
"gyroscopeXAxis": -0.001221730,
"gyroscopeYAxis": 0.031764992,
"gyroscopeZAxis": 0.007330383,
"Latitude": 39.817024734802544 ,
"Longitude": -8.624657336622477 ,
"speedKmh": 0.0 ,
"timestamp": "2023-05-05 22:19:58.817"
},
{
"id": 829,
"accelerometerXAxis": 0.169815183,
"accelerometerYAxis": 0.055618405,
"accelerometerZAxis": -0.059044838,
"gyroscopeXAxis": 0.013439035,
"gyroscopeYAxis": 0.010995574,
"gyroscopeZAxis": 0.005497787,
"Latitude": 39.817024734802544 ,
"Longitude": -8.624657336622477 ,
"speedKmh": 0.0 ,
"timestamp": "2023-05-05 22:19:59.066"
},
{
"id": 830,
"accelerometerXAxis": -0.165838361,
"accelerometerYAxis": 0.413767219,
"accelerometerZAxis": 0.006958008,
"gyroscopeXAxis": -0.000610865,
"gyroscopeYAxis": 0.020158553,
"gyroscopeZAxis": 0.038484510,
"Latitude": 39.817024734802544 ,
"Longitude": -8.624657336622477 ,
"speedKmh": 0.0 ,
"timestamp": "2023-05-05 22:19:59.317"
},
{
"id": 831,
"accelerometerXAxis": -0.351146519,
"accelerometerYAxis": 0.599560618,
"accelerometerZAxis": -0.039499283,
"gyroscopeXAxis": -0.002443461,
"gyroscopeYAxis": 0.008552114,
"gyroscopeZAxis": 0.058032200,
"Latitude": 39.817024734802544 ,
"Longitude": -8.624657336622477 ,
"speedKmh": 0.0 ,
"timestamp": "2023-05-05 22:19:59.567"
},
{
"id": 832,
"accelerometerXAxis": -0.171998024,
"accelerometerYAxis": 0.213619351,
"accelerometerZAxis": -0.192077637,
"gyroscopeXAxis": 0.003054326,
"gyroscopeYAxis": 0.015882496,
"gyroscopeZAxis": 0.095294975,
"Latitude": 39.817024734802544 ,
"Longitude": -8.624657336622477 ,
"speedKmh": 0.0 ,
"timestamp": "2023-05-05 22:19:59.817"
},
{
"id": 833,
"accelerometerXAxis": -0.261206329,
"accelerometerYAxis": 0.368635297,
"accelerometerZAxis": -0.041968346,
"gyroscopeXAxis": -0.014049901,
"gyroscopeYAxis": 0.003054326,
"gyroscopeZAxis": 0.132557765,
"Latitude": 39.817024734802544 ,
"Longitude": -8.624657336622477 ,
"speedKmh": 0.0 ,
"timestamp": "2023-05-05 22:20:00.067"
},
{
"id": 834,
"accelerometerXAxis": 0.031514287,
"accelerometerYAxis": -0.337377906,
"accelerometerZAxis": 0.186932564,
"gyroscopeXAxis": -0.015882496,
"gyroscopeYAxis": 0.014660766,
"gyroscopeZAxis": 0.181426972,
"Latitude": 39.817024734802544 ,
"Longitude": -8.624657336622477 ,
"speedKmh": 0.0 ,
"timestamp": "2023-05-05 22:20:00.318"
},
{
"id": 835,
"accelerometerXAxis": -0.234736323,
"accelerometerYAxis": -0.279136658,
"accelerometerZAxis": -0.043387413,
"gyroscopeXAxis": 0.014049901,
"gyroscopeYAxis": 0.020769419,
"gyroscopeZAxis": 0.214413702,
"Latitude": 39.81703269761056 ,
"Longitude": -8.624653313308954 ,
"speedKmh": 5.36 ,
"timestamp": "2023-05-05 22:20:00.577"
},
{
"id": 836,
"accelerometerXAxis": -0.344014525,
"accelerometerYAxis": -0.727386832,
"accelerometerZAxis": -0.386127472,
"gyroscopeXAxis": -0.063529983,
"gyroscopeYAxis": 0.016493361,
"gyroscopeZAxis": 0.287106663,
"Latitude": 39.81703269761056 ,
"Longitude": -8.624653313308954 ,
"speedKmh": 5.36 ,
"timestamp": "2023-05-05 22:20:00.826"
},
{
"id": 837,
"accelerometerXAxis": 0.364960909,
"accelerometerYAxis": -2.076056242,
"accelerometerZAxis": 1.572343826,
"gyroscopeXAxis": -0.014660766,
"gyroscopeYAxis": -0.058643065,
"gyroscopeZAxis": 0.318260789,
"Latitude": 39.81703269761056 ,
"Longitude": -8.624653313308954 ,
"speedKmh": 5.36 ,
"timestamp": "2023-05-05 22:20:01.076"
},
{
"id": 838,
"accelerometerXAxis": -0.287656665,
"accelerometerYAxis": 0.838702321,
"accelerometerZAxis": -0.853575706,
"gyroscopeXAxis": 0.060475659,
"gyroscopeYAxis": 0.097738437,
"gyroscopeZAxis": 0.364075691,
"Latitude": 39.81703269761056 ,
"Longitude": -8.624653313308954 ,
"speedKmh": 5.36 ,
"timestamp": "2023-05-05 22:20:01.331"
},
{
"id": 839,
"accelerometerXAxis": -0.292436600,
"accelerometerYAxis": -0.280056119,
"accelerometerZAxis": 0.250320435,
"gyroscopeXAxis": -0.094073251,
"gyroscopeYAxis": 0.021380283,
"gyroscopeZAxis": 0.400727600,
"Latitude": 39.8170460248366 ,
"Longitude": -8.624665550887585 ,
"speedKmh": 8.82 ,
"timestamp": "2023-05-05 22:20:01.580"
},
{
"id": 840,
"accelerometerXAxis": -0.464207888,
"accelerometerYAxis": 0.174002230,
"accelerometerZAxis": 0.134522438,
"gyroscopeXAxis": 0.000610865,
"gyroscopeYAxis": -0.032375857,
"gyroscopeZAxis": 0.405614525,
"Latitude": 39.8170460248366 ,
"Longitude": -8.624665550887585 ,
"speedKmh": 8.82 ,
"timestamp": "2023-05-05 22:20:01.830"
},
{
"id": 841,
"accelerometerXAxis": 0.511527181,
"accelerometerYAxis": 0.044008434,
"accelerometerZAxis": 0.353324890,
"gyroscopeXAxis": -0.102625363,
"gyroscopeYAxis": -0.006719518,
"gyroscopeZAxis": 0.419664413,
"Latitude": 39.8170460248366 ,
"Longitude": -8.624665550887585 ,
"speedKmh": 8.82 ,
"timestamp": "2023-05-05 22:20:02.080"
},
{
"id": 842,
"accelerometerXAxis": -0.338717818,
"accelerometerYAxis": -0.203095853,
"accelerometerZAxis": -0.876901627,
"gyroscopeXAxis": -0.046425760,
"gyroscopeYAxis": 0.086131997,
"gyroscopeZAxis": 0.427605659,
"Latitude": 39.8170460248366 ,
"Longitude": -8.624665550887585 ,
"speedKmh": 8.82 ,
"timestamp": "2023-05-05 22:20:02.332"
},
{
"id": 843,
"accelerometerXAxis": 0.262089372,
"accelerometerYAxis": -0.698899508,
"accelerometerZAxis": 0.769310951,
"gyroscopeXAxis": -0.054977871,
"gyroscopeYAxis": -0.030543262,
"gyroscopeZAxis": 0.384234250,
"Latitude": 39.81706354301423 ,
"Longitude": -8.624690948054194 ,
"speedKmh": 13.9 ,
"timestamp": "2023-05-05 22:20:02.582"
},
{
"id": 844,
"accelerometerXAxis": 0.389551163,
"accelerometerYAxis": -0.443327934,
"accelerometerZAxis": -0.220512390,
"gyroscopeXAxis": -0.036651913,
"gyroscopeYAxis": 0.037873644,
"gyroscopeZAxis": 0.329867244,
"Latitude": 39.81706354301423 ,
"Longitude": -8.624690948054194 ,
"speedKmh": 13.9 ,
"timestamp": "2023-05-05 22:20:02.833"
},
{
"id": 845,
"accelerometerXAxis": 0.031242132,
"accelerometerYAxis": 1.525377631,
"accelerometerZAxis": 0.412113190,
"gyroscopeXAxis": -0.018936822,
"gyroscopeYAxis": 0.010384710,
"gyroscopeZAxis": 0.265726388,
"Latitude": 39.81706354301423 ,
"Longitude": -8.624690948054194 ,
"speedKmh": 13.9 ,
"timestamp": "2023-05-05 22:20:03.082"
},
{
"id": 846,
"accelerometerXAxis": -0.228920698,
"accelerometerYAxis": -0.676370502,
"accelerometerZAxis": -0.009484291,
"gyroscopeXAxis": -0.044593163,
"gyroscopeYAxis": 0.026267206,
"gyroscopeZAxis": 0.260839462,
"Latitude": 39.81706354301423 ,
"Longitude": -8.624690948054194 ,
"speedKmh": 13.9 ,
"timestamp": "2023-05-05 22:20:03.348"
},
{
"id": 847,
"accelerometerXAxis": 0.576792121,
"accelerometerYAxis": 0.384195447,
"accelerometerZAxis": -0.117293358,
"gyroscopeXAxis": -0.001832596,
"gyroscopeYAxis": 0.070860371,
"gyroscopeZAxis": 0.267558992,
"Latitude": 39.81707917526364 ,
"Longitude": -8.624732857570052 ,
"speedKmh": 15.1 ,
"timestamp": "2023-05-05 22:20:03.599"
},
{
"id": 848,
"accelerometerXAxis": -0.141150355,
"accelerometerYAxis": 0.020796657,
"accelerometerZAxis": 0.538582802,
"gyroscopeXAxis": -0.022602014,
"gyroscopeYAxis": -0.001832596,
"gyroscopeZAxis": 0.207694188,
"Latitude": 39.81707917526364 ,
"Longitude": -8.624732857570052 ,
"speedKmh": 15.1 ,
"timestamp": "2023-05-05 22:20:03.849"
},
{
"id": 849,
"accelerometerXAxis": 0.092919827,
"accelerometerYAxis": -0.151644468,
"accelerometerZAxis": -0.170767784,
"gyroscopeXAxis": -0.007330383,
"gyroscopeYAxis": 0.007941248,
"gyroscopeZAxis": 0.163101017,
"Latitude": 39.81707917526364 ,
"Longitude": -8.624732857570052 ,
"speedKmh": 15.1 ,
"timestamp": "2023-05-05 22:20:04.099"
},
{
"id": 850,
"accelerometerXAxis": -0.178935051,
"accelerometerYAxis": 0.116431832,
"accelerometerZAxis": -0.564587593,
"gyroscopeXAxis": -0.001221730,
"gyroscopeYAxis": 0.003054326,
"gyroscopeZAxis": 0.111177474,
"Latitude": 39.81707917526364 ,
"Longitude": -8.624732857570052 ,
"speedKmh": 15.1 ,
"timestamp": "2023-05-05 22:20:04.349"
},
{
"id": 851,
"accelerometerXAxis": -0.126513839,
"accelerometerYAxis": 0.025609493,
"accelerometerZAxis": -0.154402733,
"gyroscopeXAxis": -0.010995574,
"gyroscopeYAxis": 0.026878070,
"gyroscopeZAxis": 0.089186326,
"Latitude": 39.81708516832441 ,
"Longitude": -8.624790692701936 ,
"speedKmh": 16.0 ,
"timestamp": "2023-05-05 22:20:04.599"
},
{
"id": 852,
"accelerometerXAxis": -0.481314421,
"accelerometerYAxis": 0.263550758,
"accelerometerZAxis": -0.201505661,
"gyroscopeXAxis": -0.005497787,
"gyroscopeYAxis": 0.015882496,
"gyroscopeZAxis": 0.081245080,
"Latitude": 39.81708516832441 ,
"Longitude": -8.624790692701936 ,
"speedKmh": 16.0 ,
"timestamp": "2023-05-05 22:20:04.849"
},
{
"id": 853,
"accelerometerXAxis": -0.054410696,
"accelerometerYAxis": -0.347133756,
"accelerometerZAxis": 0.226967812,
"gyroscopeXAxis": 0.004886922,
"gyroscopeYAxis": 0.003665192,
"gyroscopeZAxis": 0.048258353,
"Latitude": 39.81708516832441 ,
"Longitude": -8.624790692701936 ,
"speedKmh": 16.0 ,
"timestamp": "2023-05-05 22:20:05.100"
},
{
"id": 854,
"accelerometerXAxis": 0.515738785,
"accelerometerYAxis": -0.305479527,
"accelerometerZAxis": 0.068981171,
"gyroscopeXAxis": -0.002443461,
"gyroscopeYAxis": 0.009162978,
"gyroscopeZAxis": 0.004886922,
"Latitude": 39.81708516832441 ,
"Longitude": -8.624790692701936 ,
"speedKmh": 16.0 ,
"timestamp": "2023-05-05 22:20:05.362"
},
{
"id": 855,
"accelerometerXAxis": -0.011470556,
"accelerometerYAxis": 0.006895304,
"accelerometerZAxis": -0.011435509,
"gyroscopeXAxis": 0.006719518,
"gyroscopeYAxis": -0.006719518,
"gyroscopeZAxis": -0.015882496,
"Latitude": 39.817086844705045 ,
"Longitude": -8.624852132052183 ,
"speedKmh": 19.1 ,
"timestamp": "2023-05-05 22:20:05.613"
},
{
"id": 856,
"accelerometerXAxis": 0.064204991,
"accelerometerYAxis": -0.241130590,
"accelerometerZAxis": 0.064455032,
"gyroscopeXAxis": 0.000000000,
"gyroscopeYAxis": -0.006719518,
"gyroscopeZAxis": -0.037873644,
"Latitude": 39.817086844705045 ,
"Longitude": -8.624852132052183 ,
"speedKmh": 19.1 ,
"timestamp": "2023-05-05 22:20:05.865"
},
{
"id": 857,
"accelerometerXAxis": -0.114346802,
"accelerometerYAxis": 0.277727127,
"accelerometerZAxis": -0.167506218,
"gyroscopeXAxis": -0.002443461,
"gyroscopeYAxis": -0.000610865,
"gyroscopeZAxis": -0.063529983,
"Latitude": 39.817086844705045 ,
"Longitude": -8.624852132052183 ,
"speedKmh": 19.1 ,
"timestamp": "2023-05-05 22:20:06.130"
}
]

}